pydrology/__init__.py
pydrology/config.py
pydrology/plotting.py
pydrology/time_series.py
pydrology/acis/__init__.py
pydrology/acis/acis_request.py
pydrology/nexrad/__init__.py
pydrology/nexrad/nexrad_config.py
pydrology/nexrad/nexrad_download.py
pydrology/nexrad/nexrad_processing.py
pydrology/usgs/__init__.py
pydrology/usgs/usgs_prcp_request.py
pydrology/usgs/usgs_request.py
tests/__init__.py
tests/test_acis_data.py
tests/test_usgs_data.py
pydrology-1.1.2.dist-info/LICENSE
pydrology-1.1.2.dist-info/METADATA
pydrology-1.1.2.dist-info/WHEEL
pydrology-1.1.2.dist-info/top_level.txt
pydrology-1.1.2.dist-info/RECORD
