Metadata-Version: 2.1
Name: pydrology
Version: 1.1.2
Summary: A Python package for accessing and processing hydrologic data.
Home-page: https://github.com/alex-l-young/pydrology
Author: Alex Young
Author-email: pydrology@googlegroups.com
License: BSD 3-Clause License
Project-URL: Bug Tracker, https://github.com/alex-l-young/pydrology/issues
Classifier: Programming Language :: Python :: 3
Classifier: License :: OSI Approved :: BSD License
Classifier: Operating System :: OS Independent
Requires-Python: >=3.6
License-File: LICENSE
Requires-Dist: numpy
Requires-Dist: pandas
Requires-Dist: matplotlib
Requires-Dist: requests
Requires-Dist: pytest
Requires-Dist: notebook
Requires-Dist: scipy
Requires-Dist: traces
Requires-Dist: boto3
Requires-Dist: nexradaws
Requires-Dist: cftime
Requires-Dist: netCDF4
Requires-Dist: metpy
Requires-Dist: pyyaml
